amulet/pybind11_extensions/__init__.py
amulet/pybind11_extensions/_version.py
amulet/pybind11_extensions/amulet_pybind11_extensionsConfig.cmake
amulet/pybind11_extensions/builtins.hpp
amulet/pybind11_extensions/collections.hpp
amulet/pybind11_extensions/compatibility.hpp
amulet/pybind11_extensions/contextlib.hpp
amulet/pybind11_extensions/hash.hpp
amulet/pybind11_extensions/iterator.hpp
amulet/pybind11_extensions/mapping.hpp
amulet/pybind11_extensions/mutable_mapping.hpp
amulet/pybind11_extensions/nogil_holder.hpp
amulet/pybind11_extensions/numpy.hpp
amulet/pybind11_extensions/py_module.hpp
amulet/pybind11_extensions/pybind11.hpp
amulet/pybind11_extensions/sequence.hpp
amulet/pybind11_extensions/types.hpp
amulet_pybind11_extensions-1.0.0.1.dist-info/licenses/LICENSE
amulet_pybind11_extensions-1.0.0.1.dist-info/METADATA
amulet_pybind11_extensions-1.0.0.1.dist-info/WHEEL
amulet_pybind11_extensions-1.0.0.1.dist-info/top_level.txt
amulet_pybind11_extensions-1.0.0.1.dist-info/RECORD
