Metadata-Version: 2.4
Name: amulet-pybind11-extensions
Version: 1.0.0.1
Summary: An extension library for pybind11.
Author: James Clare
Project-URL: Homepage, https://www.amuletmc.com
Project-URL: Repository, https://github.com/Amulet-Team/Amulet-pybind11-extensions
Project-URL: Issues, https://github.com/Amulet-Team/Amulet-pybind11-extensions
Classifier: Programming Language :: Python :: 3
Classifier: Operating System :: OS Independent
Requires-Python: >=3.11
License-File: LICENSE
Provides-Extra: dev
Requires-Dist: setuptools>=42; extra == "dev"
Requires-Dist: versioneer; extra == "dev"
Requires-Dist: wheel; extra == "dev"
Requires-Dist: pybind11[global]==2.13.6; extra == "dev"
Requires-Dist: black>=22.3; extra == "dev"
Dynamic: license-file
